setup.py
pyExpenses/ConfigManip.py
pyExpenses/ErrorHandle.py
pyExpenses/Expense.py
pyExpenses/ProjectParse.py
pyExpenses/Projects.py
pyExpenses/RecManip.py
pyExpenses/RecManipImpl.py
pyExpenses/RecParser.py
pyExpenses/Record.py
pyExpenses/__init__.py
pyExpenses/utils.py
pyExpenses.egg-info/PKG-INFO
pyExpenses.egg-info/SOURCES.txt
pyExpenses.egg-info/dependency_links.txt
pyExpenses.egg-info/top_level.txt