Metadata-Version: 1.0
Name: pyExpenses
Version: 0.3.1
Summary: pyExpenses is a python package for simply personal financial management.
Home-page: https://github.com/JasonLai256/pyExpenses.git
Author: Jason Lai
Author-email: jasonlai256@gmail.com
License: BSD
Platform: any
Classifier: Development Status :: 3 - Alpha
Classifier: Environment :: Other Environment
Classifier: Intended Audience :: Developers
Classifier: License :: OSI Approved :: BSD License
Classifier: Operating System :: OS Independent
Classifier: Programming Language :: Python
Classifier: Topic :: Office/Business :: Financial
Classifier: Topic :: Software Development :: Libraries :: Python Modules
